{
  "players": [
    {
      "username": "101stArrow",
      "highscore": 41
    },
    {
      "username": "Blobberjob96",
      "highscore": 22
    }
  ],
  "leaderboard": [
    {
      "username": "Blobberjob96",
      "score": 0,
      "time": 1487165580147
    },
    {
      "username": "Blobberjob96",
      "score": 0,
      "time": 1487165588566
    },
    {
      "username": "Blobberjob96",
      "score": 3,
      "time": 1487165620820
    },
    {
      "username": "101stArrow",
      "score": 0,
      "time": 1487176910829
    },
    {
      "username": "101stArrow",
      "score": 29,
      "time": 1487177309482
    },
    {
      "username": "Blobberjob96",
      "score": 22,
      "time": 1487177628100
    },
    {
      "username": "101stArrow",
      "score": 0,
      "time": 1487181239621
    },
    {
      "username": "101stArrow",
      "score": 0,
      "time": 1487181264525
    },
    {
      "username": "101stArrow",
      "score": 1,
      "time": 1487181374456
    },
    {
      "username": "101stArrow",
      "score": 22,
      "time": 1487181612464
    },
    {
      "username": "101stArrow",
      "score": 7,
      "time": 1487181833148
    },
    {
      "username": "101stArrow",
      "score": 0,
      "time": 1487182234920
    },
    {
      "username": "101stArrow",
      "score": 0,
      "time": 1487182245760
    },
    {
      "username": "101stArrow",
      "score": 0,
      "time": 1487182251217
    },
    {
      "username": "101stArrow",
      "score": 0,
      "time": 1487183185561
    },
    {
      "username": "101stArrow",
      "score": 18,
      "time": 1487183348968
    },
    {
      "username": "101stArrow",
      "score": 2,
      "time": 1487183914240
    },
    {
      "username": "101stArrow",
      "score": 1,
      "time": 1487184016372
    },
    {
      "username": "101stArrow",
      "score": 0,
      "time": 1487184034961
    },
    {
      "username": "101stArrow",
      "score": 0,
      "time": 1487184244161
    },
    {
      "username": "101stArrow",
      "score": 0,
      "time": 1487184283917
    },
    {
      "username": "101stArrow",
      "score": 0,
      "time": 1487184285690
    },
    {
      "username": "101stArrow",
      "score": 0,
      "time": 1487184336802
    },
    {
      "username": "101stArrow",
      "score": 0,
      "time": 1487184363899
    },
    {
      "username": "101stArrow",
      "score": 4,
      "time": 1487184432630
    },
    {
      "username": "101stArrow",
      "score": 0,
      "time": 1487184601785
    },
    {
      "username": "101stArrow",
      "score": 5,
      "time": 1487185034895
    },
    {
      "username": "101stArrow",
      "score": 1,
      "time": 1487185330339
    },
    {
      "username": "101stArrow",
      "score": 3,
      "time": 1487185686376
    },
    {
      "username": "101stArrow",
      "score": 5,
      "time": 1487185787310
    },
    {
      "username": "101stArrow",
      "score": 10,
      "time": 1487185840389
    },
    {
      "username": "101stArrow",
      "score": 0,
      "time": 1487185919195
    },
    {
      "username": "101stArrow",
      "score": 0,
      "time": 1487185987985
    },
    {
      "username": "101stArrow",
      "score": 0,
      "time": 1487187583872
    },
    {
      "username": "101stArrow",
      "score": 38,
      "time": 1487195659114
    },
    {
      "username": "101stArrow",
      "score": 0,
      "time": 1487195711336
    },
    {
      "username": "101stArrow",
      "score": 40,
      "time": 1487195752229
    },
    {
      "username": "101stArrow",
      "score": 1,
      "time": 1487195783864
    },
    {
      "username": "101stArrow",
      "score": 1,
      "time": 1487195874490
    },
    {
      "username": "101stArrow",
      "score": 41,
      "time": 1487195910321
    },
    {
      "username": "101stArrow",
      "score": 0,
      "time": 1487198127755
    },
    {
      "username": "101stArrow",
      "score": 0,
      "time": 1487198129997
    },
    {
      "username": "101stArrow",
      "score": 0,
      "time": 1487200836794
    },
    {
      "username": "101stArrow",
      "score": 15,
      "time": 1487201652872
    },
    {
      "username": "101stArrow",
      "score": 0,
      "time": 1487201895274
    },
    {
      "username": "101stArrow",
      "score": 3,
      "time": 1487202087129
    },
    {
      "username": "101stArrow",
      "score": 20,
      "time": 1487202306504
    },
    {
      "username": "101stArrow",
      "score": 11,
      "time": 1487202404070
    },
    {
      "username": "101stArrow",
      "score": 17,
      "time": 1487202974077
    },
    {
      "username": "101stArrow",
      "score": 8,
      "time": 1487203118330
    },
    {
      "username": "101stArrow",
      "score": 10,
      "time": 1487203141112
    },
    {
      "username": "101stArrow",
      "score": 0,
      "time": 1487203143811
    },
    {
      "username": "101stArrow",
      "score": 0,
      "time": 1487203146492
    },
    {
      "username": "101stArrow",
      "score": 19,
      "time": 1487203192105
    },
    {
      "username": "101stArrow",
      "score": 24,
      "time": 1487203232164
    },
    {
      "username": "101stArrow",
      "score": 13,
      "time": 1487204188612
    },
    {
      "username": "101stArrow",
      "score": 13,
      "time": 1487204391307
    },
    {
      "username": "101stArrow",
      "score": 17,
      "time": 1487204693980
    },
    {
      "username": "101stArrow",
      "score": 0,
      "time": 1487204785402
    },
    {
      "username": "101stArrow",
      "score": 0,
      "time": 1487204790445
    },
    {
      "username": "101stArrow",
      "score": 20,
      "time": 1487204830940
    },
    {
      "username": "101stArrow",
      "score": 8,
      "time": 1487241083667
    },
    {
      "username": "101stArrow",
      "score": 8,
      "time": 1487241528085
    },
    {
      "username": "101stArrow",
      "score": 11,
      "time": 1487241570287
    },
    {
      "username": "101stArrow",
      "score": 0,
      "time": 1487241586863
    },
    {
      "username": "101stArrow",
      "score": 0,
      "time": 1487241588912
    },
    {
      "username": "101stArrow",
      "score": 17,
      "time": 1487246844520
    },
    {
      "username": "101stArrow",
      "score": 0,
      "time": 1487247084162
    },
    {
      "username": "101stArrow",
      "score": 14,
      "time": 1487247254834
    },
    {
      "username": "101stArrow",
      "score": 17,
      "time": 1487247286722
    },
    {
      "username": "101stArrow",
      "score": 4,
      "time": 1487247526126
    },
    {
      "username": "101stArrow",
      "score": 14,
      "time": 1487247732584
    },
    {
      "username": "101stArrow",
      "score": 6,
      "time": 1487247757163
    },
    {
      "username": "101stArrow",
      "score": 21,
      "time": 1487247869698
    },
    {
      "username": "101stArrow",
      "score": 0,
      "time": 1487247892569
    },
    {
      "username": "101stArrow",
      "score": 4,
      "time": 1487247917322
    },
    {
      "username": "101stArrow",
      "score": 0,
      "time": 1487247918878
    },
    {
      "username": "101stArrow",
      "score": 22,
      "time": 1487248183722
    },
    {
      "username": "101stArrow",
      "score": 13,
      "time": 1487249242765
    },
    {
      "username": "101stArrow",
      "score": 16,
      "time": 1487249322006
    },
    {
      "username": "101stArrow",
      "score": 11,
      "time": 1487249372786
    },
    {
      "username": "101stArrow",
      "score": 0,
      "time": 1487249839516
    },
    {
      "username": "101stArrow",
      "score": 34,
      "time": 1487250175054
    },
    {
      "username": "101stArrow",
      "score": 26,
      "time": 1487250387973
    },
    {
      "username": "101stArrow",
      "score": 0,
      "time": 1487250397040
    },
    {
      "username": "101stArrow",
      "score": 27,
      "time": 1487250581283
    }
  ],
  "champion": {
    "username": "101stArrow",
    "score": 41,
    "time": 1487195910321
  },
  "ingame": []
}